swaj/__init__.py
swaj/app.py
swaj-0.6.data/scripts/swaj
swaj-0.6.dist-info/LICENSE
swaj-0.6.dist-info/METADATA
swaj-0.6.dist-info/WHEEL
swaj-0.6.dist-info/top_level.txt
swaj-0.6.dist-info/RECORD
